<?xml version="1.0" encoding="UTF-8"?>
<office:document-content xmlns:meta="urn:oasis:names:tc:opendocument:xmlns:meta:1.0" xmlns:office="urn:oasis:names:tc:opendocument:xmlns:office:1.0" xmlns:fo="urn:oasis:names:tc:opendocument:xmlns:xsl-fo-compatible:1.0" xmlns:ooo="http://openoffice.org/2004/office" xmlns:xlink="http://www.w3.org/1999/xlink" xmlns:dc="http://purl.org/dc/elements/1.1/" xmlns:style="urn:oasis:names:tc:opendocument:xmlns:style:1.0" xmlns:text="urn:oasis:names:tc:opendocument:xmlns:text:1.0" xmlns:draw="urn:oasis:names:tc:opendocument:xmlns:drawing:1.0" xmlns:dr3d="urn:oasis:names:tc:opendocument:xmlns:dr3d:1.0" xmlns:svg="urn:oasis:names:tc:opendocument:xmlns:svg-compatible:1.0" xmlns:chart="urn:oasis:names:tc:opendocument:xmlns:chart:1.0" xmlns:rpt="http://openoffice.org/2005/report" xmlns:table="urn:oasis:names:tc:opendocument:xmlns:table:1.0" xmlns:number="urn:oasis:names:tc:opendocument:xmlns:datastyle:1.0" xmlns:ooow="http://openoffice.org/2004/writer" xmlns:oooc="http://openoffice.org/2004/calc" xmlns:of="urn:oasis:names:tc:opendocument:xmlns:of:1.2" xmlns:tableooo="http://openoffice.org/2009/table" xmlns:calcext="urn:org:documentfoundation:names:experimental:calc:xmlns:calcext:1.0" xmlns:drawooo="http://openoffice.org/2010/draw" xmlns:loext="urn:org:documentfoundation:names:experimental:office:xmlns:loext:1.0" xmlns:field="urn:openoffice:names:experimental:ooo-ms-interop:xmlns:field:1.0" xmlns:math="http://www.w3.org/1998/Math/MathML" xmlns:form="urn:oasis:names:tc:opendocument:xmlns:form:1.0" xmlns:script="urn:oasis:names:tc:opendocument:xmlns:script:1.0" xmlns:dom="http://www.w3.org/2001/xml-events" xmlns:xforms="http://www.w3.org/2002/xforms" xmlns:xsd="http://www.w3.org/2001/XMLSchema" xmlns:xsi="http://www.w3.org/2001/XMLSchema-instance" xmlns:formx="urn:openoffice:names:experimental:ooxml-odf-interop:xmlns:form:1.0" xmlns:xhtml="http://www.w3.org/1999/xhtml" xmlns:grddl="http://www.w3.org/2003/g/data-view#" xmlns:css3t="http://www.w3.org/TR/css3-text/" xmlns:officeooo="http://openoffice.org/2009/office" office:version="1.3"><office:scripts/><office:font-face-decls><style:font-face style:name="Lohit Devanagari1" svg:font-family="&apos;Lohit Devanagari&apos;"/><style:font-face style:name="AR PL SungtiL GB1" svg:font-family="&apos;AR PL SungtiL GB&apos;" style:font-family-generic="modern" style:font-pitch="fixed"/><style:font-face style:name="Liberation Mono" svg:font-family="&apos;Liberation Mono&apos;" style:font-family-generic="modern" style:font-pitch="fixed"/><style:font-face style:name="Liberation Serif" svg:font-family="&apos;Liberation Serif&apos;" style:font-family-generic="roman" style:font-pitch="variable"/><style:font-face style:name="Liberation Sans" svg:font-family="&apos;Liberation Sans&apos;" style:font-family-generic="swiss" style:font-pitch="variable"/><style:font-face style:name="AR PL SungtiL GB" svg:font-family="&apos;AR PL SungtiL GB&apos;" style:font-family-generic="system" style:font-pitch="variable"/><style:font-face style:name="Lohit Devanagari" svg:font-family="&apos;Lohit Devanagari&apos;" style:font-family-generic="system" style:font-pitch="variable"/></office:font-face-decls><office:automatic-styles/><office:body><office:text text:use-soft-page-breaks="true"><text:sequence-decls><text:sequence-decl text:display-outline-level="0" text:name="Illustration"/><text:sequence-decl text:display-outline-level="0" text:name="Table"/><text:sequence-decl text:display-outline-level="0" text:name="Text"/><text:sequence-decl text:display-outline-level="0" text:name="Drawing"/><text:sequence-decl text:display-outline-level="0" text:name="Figure"/></text:sequence-decls><text:p text:style-name="Preformatted_20_Text">Il [s&apos;agit] [d&apos;un jeune homme] [de 17 ans] , qui [se présente] [à la clinique] [de dermatologie] [pour le suivi] <text:span text:style-name="ne-connais-pas">[de son traitement de l&apos;acné vulgaire]</text:span> <text:span text:style-name="ne-connais-pas">[par l&apos;isotrétinoïne]</text:span> . <text:s/>[Lors de l&apos;anamnèse] , [le patient] [se plaint] <text:span text:style-name="pas-sur-de-comprendre">[de transpirations excessives ,]</text:span> [d&apos;une augmentation graduelle de l&apos;intensité]<text:span text:style-name="ne-connais-pas"> [de céphalées frontales récidivantes]</text:span> [et d&apos;une diminution de la vision] . <text:s/>On [demande] [une consultation] [en neurologie] . <text:s/>[Lors de la visite] , [le neurologue] [découvre] [fortuitement] <text:span text:style-name="ne-connais-pas">[une hypertension artérielle]</text:span> [atteignant] [des valeurs] [de 185] / [120 mm] <text:span text:style-name="ne-connais-pas">[Hg] </text:span>. <text:s/>[Le patient] [est] [asymptomatique] , mais [l&apos;examen] [du fond de l&apos;oeil] [est] [douteux] . <text:s/>Il [est admis] [en pédiatrie] [pour subir] [des investigations] . <text:s/></text:p><text:p text:style-name="Preformatted_20_Text"/><text:p text:style-name="Preformatted_20_Text"><text:s/></text:p><text:p text:style-name="Preformatted_20_Text"/><text:p text:style-name="Preformatted_20_Text"><text:s/>[Le patient] [est] [traité] <text:span text:style-name="ne-connais-pas">[pour une acné vulgaire ,]</text:span> <text:span text:style-name="ne-connais-pas">[des céphalées frontales récidivantes]</text:span> et [de l&apos;asthme] , pour lesquels il [reçoit] <text:span text:style-name="ne-connais-pas">[de l&apos;isotrétinoïne]</text:span> [40 mg] [par voie orale] [une fois] [par jour] ,<text:span text:style-name="ne-connais-pas"> [de l&apos;acétaminophène] </text:span>[par voie orale] [au besoin] , <text:span text:style-name="ne-connais-pas">[du salbutamol]</text:span> [en inhalation] [au besoin] et <text:span text:style-name="ne-connais-pas">[de la fluticasone] </text:span>[en inhalation] [au besoin] . <text:s/>Il [souffre] [par ailleurs] [d&apos;allergies saisonnières ,] <text:span text:style-name="ne-connais-pas">[d&apos;hypercholestérolémie secondaire] </text:span>[à la prise] <text:span text:style-name="ne-connais-pas">[d&apos;isotrétinoïne] </text:span><text:span text:style-name="pas-sur-de-comprendre">[et de myopie]</text:span> [nécessitant] [le port] [de verres correcteurs] . <text:s/>[Son frère jumeau identique] [est également atteint] <text:span text:style-name="ne-connais-pas">[d&apos;acné vulgaire et]</text:span> [d&apos;asthme] . <text:s/>[Aucun antécédent familial] <text:span text:style-name="ne-connais-pas">[d&apos;hypertension ,]</text:span> <text:span text:style-name="ne-connais-pas">[de néphropathie ,] [de néoplasme de la glande thyroïde] </text:span>et [des glandes surrénales] [n&apos;est noté] [à l&apos;anamnèse] . <text:s/></text:p><text:p text:style-name="Preformatted_20_Text"/><text:p text:style-name="Preformatted_20_Text"><text:s/></text:p><text:p text:style-name="Preformatted_20_Text"/><text:p text:style-name="Preformatted_20_Text"><text:s/>[À son admission] , [le patient] [a] <text:span text:style-name="ne-connais-pas">[une tension artérielle]</text:span> [et une fréquence cardiaque] qui [s&apos;élèvent] [respectivement] [à 184] / [112 mm] <text:span text:style-name="ne-connais-pas">[Hg]</text:span> et [à 96 battements] [par minute] . <text:s/>Il [est] [asymptomatique] . <text:s/>[Le reste] [de l&apos;examen physique] [ne révèle] [aucune particularité] . <text:s/>On lui [prescrit] [un dosage] <text:span text:style-name="ne-connais-pas">[des cathécolamines et] [de leurs métabolites]</text:span> [sur une collecte urinaire] [de 24 heures] . <text:s/>On [commence] à lui [donner] <text:span text:style-name="ne-connais-pas">[de la nifédipine]</text:span> [quelques heures] [plus] [tard] [en raison d&apos;une augmentation] [de la tension artérielle] , qui [atteint] [des valeurs supérieures] [à 200] / [130 mm] <text:span text:style-name="ne-connais-pas">[Hg]</text:span> . <text:s/>[La liste] [des médicaments] [reçus] [durant l&apos;hospitalisation] [se trouve] [au tableau] I . <text:s/></text:p><text:p text:style-name="Preformatted_20_Text"/><text:p text:style-name="Preformatted_20_Text"><text:s/></text:p><text:p text:style-name="Preformatted_20_Text"/><text:p text:style-name="Preformatted_20_Text"><text:s/>[Au jour] [2] , [la tension artérielle]<text:span text:style-name="par-défaut"> [et la fréquence cardiaque du patient] </text:span>[atteignent] [respectivement] [191] / [95 mm] <text:span text:style-name="ne-connais-pas">[Hg]</text:span> [et 125 battements] [par minute] . <text:s/>[Le jeune homme] [présente] <text:span text:style-name="ne-connais-pas">[une légère céphalée] </text:span>. <text:s/>On [ajuste] [les doses] <text:span text:style-name="ne-connais-pas">[de nifédipine] . <text:s/>[L&apos;échographie abdominale et pelvienne] </text:span>[révèle] [la présence] <text:span text:style-name="ne-connais-pas">[d&apos;une masse surrénalienne]</text:span> [à droite] . <text:s/>On [suspecte]<text:span text:style-name="ne-connais-pas"> [un phéochromocytome]</text:span> , et on [prescrit] [au patient] <text:span text:style-name="ne-connais-pas">[de la phénoxybenzamine]</text:span> . <text:s/>[L&apos;examen ophtalmique] [révèle] [l&apos;absence]<text:span text:style-name="ne-connais-pas"> [de papilloedème]</text:span> . <text:s/></text:p><text:p text:style-name="Preformatted_20_Text"/><text:p text:style-name="Preformatted_20_Text"><text:s/></text:p><text:p text:style-name="Preformatted_20_Text"/><text:p text:style-name="Preformatted_20_Text"><text:s/>[Au jour] [3] , on [note] [deux épisodes] <text:span text:style-name="ne-connais-pas">[d&apos;hypotension orthostatique]</text:span> . <text:s/>[La tension artérielle] [est] [transitoire] . <text:s/>[La dose] <text:span text:style-name="ne-connais-pas">[de phénoxybenzamine]</text:span> [est réévaluée] [à la baisse] , on [cesse] [d&apos;administrer]<text:span text:style-name="ne-connais-pas"> [la nifédipine] </text:span>, et on [commence] <text:span text:style-name="ne-connais-pas">[un remplissage vasculaire]</text:span> . <text:s/>[Le dosage] <text:span text:style-name="ne-connais-pas">[des catécholamines plasmatiques]</text:span> [révèle] [une augmentation] <text:span text:style-name="ne-connais-pas">[de la norépinéphrine et] [de l&apos;épinéphrine] </text:span>. <text:s/>[Le dosage] <text:span text:style-name="ne-connais-pas">[de thyrothropine ,]</text:span> <text:span text:style-name="ne-connais-pas">[de parathormone] </text:span>et <text:span text:style-name="ne-connais-pas">[d&apos;aldostérone]</text:span> [est] [normal] . <text:span text:style-name="ne-connais-pas"><text:s/>[L&apos;électrocardiogramme]</text:span> [ne révèle] rien [d&apos;anormal] . <text:s/>On [annule]<text:span text:style-name="ne-connais-pas"> [la tomodensitométrie cérébrale]</text:span> [avec coupe fine] [au niveau du nerf optique] . <text:s/>[En lieu et place] , on [réalise] [une imagerie]<text:span text:style-name="ne-connais-pas"> [par résonance magnétique cérébrale] . <text:s/></text:span></text:p><text:p text:style-name="Preformatted_20_Text"><text:soft-page-break/></text:p><text:p text:style-name="Preformatted_20_Text"><text:s/></text:p><text:p text:style-name="Preformatted_20_Text"/><text:p text:style-name="Preformatted_20_Text"><text:s/>[Au jour] [5] ,<text:span text:style-name="ne-connais-pas"> [la tension artérielle systolique] </text:span>[du patient] [varie] [entre 140 et 170 mm] <text:span text:style-name="ne-connais-pas">[Hg]</text:span> , tandis que <text:span text:style-name="ne-connais-pas">[sa tension artérielle diastolique] </text:span>[avoisine] [90 mm] [Hg] . <text:s/>On lui [fait] [une injection] <text:span text:style-name="ne-connais-pas">[de 99 mTc-acide méthylènediphosphonique] </text:span>[en vue de pratiquer] <text:span text:style-name="ne-connais-pas">[une scintigraphie] [à la méta -iodo-benzylguanidine]</text:span> ( MIBG ) . <text:s/>[Lors de la confirmation] [du diagnostic] , [le généticien] [suggère] [de pratiquer] <text:span text:style-name="pas-sur-de-comprendre">[une évaluation moléculaire]</text:span> [au patient ,] [à son frère jumeau identique] [ainsi qu&apos;] [à ses parents] . <text:s/>[Au jour] [9] , [le dosage] <text:span text:style-name="ne-connais-pas">[des catécholamines] </text:span>et<text:span text:style-name="ne-connais-pas"> [de leurs métabolites urinaires]</text:span> [révèle] [une augmentation] <text:span text:style-name="ne-connais-pas">[de la norépinéphrine et] [de la normétanéphrine] . <text:s/>[La scintigraphie]</text:span> à la MIBG [ne démontre] <text:span text:style-name="pas-sur-de-comprendre">[aucune captation anormale] </text:span>. <text:s/>[L&apos;imagerie] <text:span text:style-name="ne-connais-pas">[par résonance magnétique abdominale]</text:span> [confirme] [la présence] <text:span text:style-name="ne-connais-pas">[d&apos;une masse surrénalienne]</text:span> [à droite] . <text:s/>On [note] [un foyer] <text:span text:style-name="ne-connais-pas">[d&apos;hypercaptation]</text:span> [au pôle inférieur] <text:span text:style-name="ne-connais-pas">[du lobe thyroïdien]</text:span> . <text:s/>[Au jour] [11] ,<text:span text:style-name="ne-connais-pas"> [une tomographie] </text:span>[d&apos;émission] <text:span text:style-name="ne-connais-pas">[par positrons]</text:span> [démontre] [la présence] [de graisse brune] <text:span text:style-name="ne-connais-pas">[au niveau de la surrénale droite]</text:span> . <text:s/>[L&apos;imagerie] <text:span text:style-name="ne-connais-pas">[par résonance magnétique cervicale]</text:span> [est] [normale] . <text:s/></text:p><text:p text:style-name="Preformatted_20_Text"/><text:p text:style-name="Preformatted_20_Text"><text:s/></text:p><text:p text:style-name="Preformatted_20_Text"/><text:p text:style-name="Preformatted_20_Text"><text:s/>[Au jour] [15] , <text:span text:style-name="pas-sur-de-comprendre">[lors d&apos;une réunion multidisciplinaire]</text:span> , on [décide] [d&apos;effectuer] , [au jour] [18] , [une résection]<text:span text:style-name="ne-connais-pas"> [de la glande surrénale droite]</text:span> [avec une exploration] <text:span text:style-name="ne-connais-pas">[de la glande surrénale gauche] </text:span>. <text:s/>On [commence] [immédiatement] [l&apos;administration] <text:span text:style-name="ne-connais-pas">[de métoprolol]</text:span> . <text:s/>[La veille] [de la chirurgie] , on [effectue] <text:span text:style-name="pas-sur-de-comprendre">[un remplissage vasculaire]</text:span> . <text:s/><text:span text:style-name="ne-connais-pas">[L&apos;échographie] [de la glande thyroïdienne]</text:span> [ne révèle] [aucune anomalie] . <text:s/>[Au jour] [16] , on [observe] [une diminution marquée] [de la fréquence cardiaque] [à la suite de l&apos;introduction] <text:span text:style-name="ne-connais-pas">[du métoprolol] </text:span>. <text:s/>[Les valeurs] [de la fréquence cardiaque] [avoisinent] [désormais] [70 battements] [par minute] [au lieu des 120 battements] [par minute] [précédemment] . <text:s/>[La tension artérielle] [du patient] [a légèrement diminué] , mais elle [demeure] [stable] . <text:s/></text:p><text:p text:style-name="Preformatted_20_Text"/><text:p text:style-name="Preformatted_20_Text"><text:s/></text:p><text:p text:style-name="Preformatted_20_Text"/><text:p text:style-name="Preformatted_20_Text"><text:s/>[Au jour] [18] , on [effectue] [une exérèse] [de la tumeur] <text:span text:style-name="ne-connais-pas">[par laparotomie]</text:span> . <text:s/>On [note] [un épisode] <text:span text:style-name="ne-connais-pas">[d&apos;hypotension]</text:span> qui [répond] [à l&apos;administration] <text:span text:style-name="ne-connais-pas">[de crystalloïde] , [de colloïde]</text:span> et <text:span text:style-name="ne-connais-pas">[de norépinéphrine]</text:span> . <text:s/>Une fois que [le sevrage] <text:span text:style-name="ne-connais-pas">[de la norépinéphrine]</text:span> [est achevé] , [le patient] [est transféré] [à l&apos;unité] [de soins intensifs] . <text:s/>[Le rapport] <text:span text:style-name="ne-connais-pas">[d&apos;anatomo-pathologie]</text:span> [confirme] [la présence] [d&apos;un phéochromocytome] , [sans invasion vasculaire] , <text:span text:style-name="ne-connais-pas">[avec foyers nécrotiques]</text:span> . <text:s/>[Au jour] [19] , [les valeurs] <text:span text:style-name="pas-sur-de-comprendre">[de la tension artérielle]</text:span> [du patient] [sont] [normales] , et on le [transfère] [dans l&apos;unité] [de chirurgie] . <text:s/></text:p><text:p text:style-name="Preformatted_20_Text"/><text:p text:style-name="Preformatted_20_Text"><text:s/></text:p><text:p text:style-name="Preformatted_20_Text"/><text:p text:style-name="Preformatted_20_Text"><text:s/>[Au jour] [20] , [le résident] [de garde] [est] [appelé] [auprès du patient] , car on [suspecte] [une surcharge liquidienne] . <text:s/>On [administre] [au patient] [une dose]<text:span text:style-name="ne-connais-pas"> [de furosémide] </text:span>. <text:s/>[Au jour] [21] , <text:span text:style-name="pas-sur-de-comprendre">[la tension artérielle]</text:span> [demeure] [dans les valeurs normales] . <text:s/><text:span text:style-name="ne-connais-pas">[La radiographie pulmonaire]</text:span> [révèle] [la présence] <text:span text:style-name="pas-sur-de-comprendre">[d&apos;un infiltrat] [à la base pulmonaire]</text:span> [droite] . <text:s/>On lui [administre] <text:span text:style-name="ne-connais-pas">[de la lévofloxacine] </text:span>, on lui [prescrit] [une seconde dose] <text:span text:style-name="ne-connais-pas">[de furosémide]</text:span> , et on [diminue] [le débit] [du soluté] . <text:s/>[Au jour] [23] , on [cesse] [l&apos;antibiothérapie] [en l&apos;absence de signes cliniques] [de pneumonie] . <text:s/>On [note] [une amélioration] [de la surcharge liquidienne] . <text:s/>[Au jour] [25] , [le patient] [reçoit] [son congé] [de l&apos;hôpital] . <text:s/><text:span text:style-name="pas-sur-de-comprendre">[Sa tension artérielle] </text:span>[s&apos;élève] [à 115] / [60 mm]<text:span text:style-name="ne-connais-pas"> [Hg]</text:span> . <text:s/>[Une semaine] [plus] [tard] , on [réalisera] [un dosage] <text:span text:style-name="ne-connais-pas">[des catécholamines et] [de leurs métabolites urinaires] </text:span>. <text:s/>[Le patient] [bénéficiera] [d&apos;un suivi] [à domicile] <text:span text:style-name="pas-sur-de-comprendre">[pour sa tension artérielle]</text:span> . <text:s/></text:p><text:p text:style-name="Preformatted_20_Text"><text:soft-page-break/></text:p><text:p text:style-name="Preformatted_20_Text"><text:s text:c="7"/></text:p></office:text></office:body></office:document-content>